morse_code_tool/__main__.py
morse_code_tool/morse.py
morse_code_tool-0.5.6.dist-info/METADATA
morse_code_tool-0.5.6.dist-info/WHEEL
morse_code_tool-0.5.6.dist-info/licenses/LICENSE
morse_code_tool-0.5.6.dist-info/RECORD
