Metadata-Version: 2.4
Name: morse_code_tool
Version: 0.5.6
Summary: A morse code generator
Project-URL: Homepage, https://github.com/Wdboyes13/morse_code
Project-URL: Issues, https://github.com/Wdboyes13/morse_code/issues
Author-email: Wdboyes13 <willdev2025@outlook.com>
License-Expression: MIT
License-File: LICENSE
Classifier: Operating System :: OS Independent
Classifier: Programming Language :: Python :: 3
Requires-Python: >=3.9
Requires-Dist: numpy
Requires-Dist: sounddevice
